tangens/__init__.py
tangens/base/__init__.py
tangens/base/delta.py
tangens/base/dual.py
tangens/base/eval.py
tangens/base/expression.py
tangens/base/num.py
tangens/floats/__init__.py
tangens/floats/first.py
tangens/py.typed
tangens-0.1.2.dist-info/LICENSE
tangens-0.1.2.dist-info/METADATA
tangens-0.1.2.dist-info/WHEEL
tangens-0.1.2.dist-info/RECORD
