Metadata-Version: 2.1
Name: tangens
Version: 0.1.2
Summary: Automatic differentiation library for python
Home-page: https://github.com/cospectrum/tangens
License: Apache-2.0
Author: cospectrum
Author-email: severinalexeyv@gmail.com
Requires-Python: >=3.10,<4.0
Classifier: License :: OSI Approved :: Apache Software License
Classifier: Programming Language :: Python :: 3
Classifier: Programming Language :: Python :: 3.10
Classifier: Programming Language :: Python :: 3.11
Project-URL: Repository, https://github.com/cospectrum/tangens
